geo3d/__init__.py
geo3d/auxiliary.py
geo3d/fit.py
geo3d/frame.py
geo3d/linalg.py
geo3d/plane.py
geo3d/point.py
geo3d/quaternion.py
geo3d/query.py
geo3d/rotation.py
geo3d/types.py
geo3d/units.py
geo3d/vector.py
geo3d-1.3.2.dist-info/licenses/LICENSE.txt
geo3d-1.3.2.dist-info/METADATA
geo3d-1.3.2.dist-info/WHEEL
geo3d-1.3.2.dist-info/top_level.txt
geo3d-1.3.2.dist-info/RECORD
