Metadata-Version: 2.4
Name: geo3d
Version: 1.3.2
Summary: A python package for performing geometric calculations in 3D
Author-email: "L. Riegger" <lri@me.com>
License: MIT License
Project-URL: Homepage, https://github.com/himbeles/geo3d
Project-URL: Repository, https://github.com/himbeles/geo3d.git
Project-URL: Documentation, https://himbeles.github.io/geo3d/
Keywords: geometry
Requires-Python: >=3.11
License-File: LICENSE.txt
Requires-Dist: numpy>=1.20
Requires-Dist: scipy>=1.6
Requires-Dist: numba>=0.53.0
Dynamic: license-file
